mdbrun/__init__.py
mdbrun/__main__.py
mdbrun/create.py
mdbrun/db.py
mdbrun/details.py
mdbrun/extract.py
mdbrun/fasta.py
mdbrun/main.py
mdbrun/table.py
mdbrun/taxids.py
markerdb-0.4.0.dist-info/METADATA
markerdb-0.4.0.dist-info/WHEEL
markerdb-0.4.0.dist-info/entry_points.txt
markerdb-0.4.0.dist-info/top_level.txt
markerdb-0.4.0.dist-info/RECORD
