Metadata-Version: 2.1
Name: markerdb
Version: 0.4.0
Summary: markerdb
Home-page: https://github.com/aswathyseb/markerdb
Author: Aswathy Sebastian
Author-email: aswathyseb@gmail.com
Classifier: Programming Language :: Python :: 3
Classifier: License :: OSI Approved :: MIT License
Classifier: Operating System :: OS Independent
Requires-Python: >=3.6
Requires-Dist: plac
